{
  "version": "7",
  "dialect": "postgresql",
  "entries": [
    {
      "idx": 0,
      "version": "7",
      "when": 1737139025213,
      "tag": "0000_wet_spot",
      "breakpoints": true
    },
    {
      "idx": 1,
      "version": "7",
      "when": 1737294041876,
      "tag": "0001_misty_mach_iv",
      "breakpoints": true
    },
    {
      "idx": 2,
      "version": "7",
      "when": 1737294534784,
      "tag": "0002_freezing_piledriver",
      "breakpoints": true
    },
    {
      "idx": 3,
      "version": "7",
      "when": 1737381482292,
      "tag": "0003_volatile_tyrannus",
      "breakpoints": true
    },
    {
      "idx": 4,
      "version": "7",
      "when": 1737381531863,
      "tag": "0004_heavy_blade",
      "breakpoints": true
    },
    {
      "idx": 5,
      "version": "7",
      "when": 1737381778484,
      "tag": "0005_unknown_thor_girl",
      "breakpoints": true
    },
    {
      "idx": 6,
      "version": "7",
      "when": 1737383697341,
      "tag": "0006_rapid_proudstar",
      "breakpoints": true
    },
    {
      "idx": 7,
      "version": "7",
      "when": 1737383775236,
      "tag": "0007_sweet_bug",
      "breakpoints": true
    },
    {
      "idx": 8,
      "version": "7",
      "when": 1737383822452,
      "tag": "0008_lucky_tattoo",
      "breakpoints": true
    },
    {
      "idx": 9,
      "version": "7",
      "when": 1737383859525,
      "tag": "0009_slippery_smasher",
      "breakpoints": true
    },
    {
      "idx": 10,
      "version": "7",
      "when": 1737384010896,
      "tag": "0010_sharp_vindicator",
      "breakpoints": true
    },
    {
      "idx": 11,
      "version": "7",
      "when": 1737385033757,
      "tag": "0011_bumpy_donald_blake",
      "breakpoints": true
    },
    {
      "idx": 12,
      "version": "7",
      "when": 1737385376640,
      "tag": "0012_previous_salo",
      "breakpoints": true
    },
    {
      "idx": 13,
      "version": "7",
      "when": 1737385485616,
      "tag": "0013_flat_jasper_sitwell",
      "breakpoints": true
    },
    {
      "idx": 14,
      "version": "7",
      "when": 1737483304341,
      "tag": "0014_wealthy_clint_barton",
      "breakpoints": true
    },
    {
      "idx": 15,
      "version": "7",
      "when": 1737571223785,
      "tag": "0015_square_ikaris",
      "breakpoints": true
    },
    {
      "idx": 16,
      "version": "7",
      "when": 1737571449354,
      "tag": "0016_lazy_karma",
      "breakpoints": true
    },
    {
      "idx": 17,
      "version": "7",
      "when": 1737572187303,
      "tag": "0017_loving_tenebrous",
      "breakpoints": true
    }
  ]
}